inventory_app/__init__.py
inventory_app/database.py
inventory_app/main.py
ux3270/__init__.py
ux3270/dialog/__init__.py
ux3270/dialog/form.py
ux3270/dialog/layout.py
ux3270/dialog/menu.py
ux3270/dialog/message.py
ux3270/dialog/selection_list.py
ux3270/dialog/table.py
ux3270/dialog/tabular_entry.py
ux3270/dialog/work_with_list.py
ux3270/panel/__init__.py
ux3270/panel/colors.py
ux3270/panel/field.py
ux3270/panel/screen.py
ux3270-1.0.1.dist-info/METADATA
ux3270-1.0.1.dist-info/WHEEL
ux3270-1.0.1.dist-info/entry_points.txt
ux3270-1.0.1.dist-info/licenses/LICENSE
ux3270-1.0.1.dist-info/RECORD
