Metadata-Version: 2.4
Name: ux3270
Version: 1.0.1
Summary: IBM 3270-like terminal UI library for Python
Project-URL: Homepage, https://github.com/ljosa/ux3270
Project-URL: Documentation, https://ljosa.github.io/ux3270/
Project-URL: Repository, https://github.com/ljosa/ux3270
Author: Vebjorn Ljosa
License-Expression: MIT
License-File: LICENSE
Keywords: 3270,cli,forms,ibm,terminal,tui
Classifier: Development Status :: 5 - Production/Stable
Classifier: Environment :: Console
Classifier: Intended Audience :: Developers
Classifier: License :: OSI Approved :: MIT License
Classifier: Operating System :: POSIX
Classifier: Programming Language :: Python :: 3
Classifier: Programming Language :: Python :: 3.10
Classifier: Programming Language :: Python :: 3.11
Classifier: Programming Language :: Python :: 3.12
Classifier: Programming Language :: Python :: 3.13
Classifier: Topic :: Software Development :: Libraries :: Python Modules
Classifier: Topic :: Terminals
Requires-Python: >=3.10
